{"cameraMode":{"drawMode":0,"name":"Shaded","section":"Shading Mode"},"sceneLighting":true,"audioPlay":false,"sceneViewState":{"m_AlwaysRefresh":false,"showFog":true,"showSkybox":true,"showFlares":true,"showImageEffects":true,"showParticleSystems":true,"showVisualEffectGraphs":true,"m_FxEnabled":true},"in2DMode":false,"pivot":{"x":-1.5,"y":0.0,"z":-2.499998092651367},"rotation":{"x":-0.2493411749601364,"y":0.0002870082971639931,"z":-0.00007379715680144727,"w":-0.9684160351753235},"size":23.710290908813478,"orthographic":true}